google/protobuf/descriptor_rbt.py
google/protobuf/empty_rbt.py
google/protobuf/struct_rbt.py
rbt/mcp/v1/session.proto
rbt/mcp/v1/session_pb2.py
rbt/mcp/v1/session_pb2.pyi
rbt/mcp/v1/session_pb2_grpc.py
rbt/mcp/v1/session_rbt.py
rbt/mcp/v1/stream.proto
rbt/mcp/v1/stream_pb2.py
rbt/mcp/v1/stream_pb2.pyi
rbt/mcp/v1/stream_pb2_grpc.py
rbt/mcp/v1/stream_rbt.py
rbt/v1alpha1/options_rbt.py
reboot/mcp/client.py
reboot/mcp/event_store.py
reboot/mcp/server.py
reboot/mcp/servicers/session.py
reboot/mcp/servicers/stream.py
durable_mcp-0.6.0.dist-info/METADATA
durable_mcp-0.6.0.dist-info/WHEEL
durable_mcp-0.6.0.dist-info/licenses/LICENSE
durable_mcp-0.6.0.dist-info/RECORD
