Metadata-Version: 2.4
Name: durable-mcp
Version: 0.6.0
Summary: Durable Model Context Protocol (MCP) helpers for building resumable MCP servers on top of Reboot durable workflows.
Project-URL: Homepage, https://github.com/reboot-dev/mcp-python
Project-URL: Repository, https://github.com/reboot-dev/mcp-python
Project-URL: Issues, https://github.com/reboot-dev/mcp-python/issues
Author-email: Reboot <team@reboot.dev>
License:                                  Apache License
License-File: LICENSE
Keywords: durable,mcp,model-context-protocol,reboot,workflows
Classifier: Development Status :: 2 - Pre-Alpha
Classifier: Intended Audience :: Developers
Classifier: License :: OSI Approved :: Apache Software License
Classifier: Programming Language :: Python
Classifier: Programming Language :: Python :: 3
Classifier: Programming Language :: Python :: 3.12
Classifier: Topic :: Internet :: WWW/HTTP
Classifier: Topic :: Software Development :: Libraries
Classifier: Typing :: Typed
Requires-Python: >=3.12.11
Requires-Dist: mcp==1.21.0
Requires-Dist: reboot==0.40.1
Requires-Dist: uuid7-standard>=1.1.0
Provides-Extra: dev
Requires-Dist: build; extra == 'dev'
Requires-Dist: mypy==1.2.0; extra == 'dev'
Requires-Dist: pytest==8.4.1; extra == 'dev'
Requires-Dist: twine; extra == 'dev'
Requires-Dist: types-protobuf>=4.24.0.20240129; extra == 'dev'
